Metadata-Version: 2.1
Name: cheroot-cc
Version: 6.5.4
Summary: Highly-optimized, pure-python HTTP server
Home-page: https://cheroot.cherrypy.org
Author: CherryPy Team
Author-email: team@cherrypy.org
License: UNKNOWN
Project-URL: CI: AppVeyor, https://ci.appveyor.com/project/cherrypy/cheroot
Project-URL: CI: Travis, https://travis-ci.org/cherrypy/cheroot
Project-URL: CI: Circle, https://circleci.com/gh/cherrypy/cheroot
Project-URL: Docs: RTD, https://cheroot.cherrypy.org
Project-URL: GitHub: issues, https://github.com/cherrypy/cheroot/issues
Project-URL: GitHub: repo, https://github.com/cherrypy/cheroot
Keywords: http,server,ssl,wsgi
Platform: UNKNOWN
Classifier: Development Status :: 5 - Production/Stable
Classifier: Environment :: Web Environment
Classifier: Intended Audience :: Developers
Classifier: Operating System :: OS Independent
Classifier: Framework :: CherryPy
Classifier: License :: OSI Approved :: BSD License
Classifier: Programming Language :: Python
Classifier: Programming Language :: Python :: 2
Classifier: Programming Language :: Python :: 2.7
Classifier: Programming Language :: Python :: 3
Classifier: Programming Language :: Python :: 3.4
Classifier: Programming Language :: Python :: 3.5
Classifier: Programming Language :: Python :: 3.6
Classifier: Programming Language :: Python :: 3.7
Classifier: Programming Language :: Python :: Implementation
Classifier: Programming Language :: Python :: Implementation :: CPython
Classifier: Programming Language :: Python :: Implementation :: Jython
Classifier: Programming Language :: Python :: Implementation :: PyPy
Classifier: Topic :: Internet :: WWW/HTTP
Classifier: Topic :: Internet :: WWW/HTTP :: HTTP Servers
Classifier: Topic :: Internet :: WWW/HTTP :: WSGI
Classifier: Topic :: Internet :: WWW/HTTP :: WSGI :: Server
Requires-Python: >=2.7,!=3.0.*,!=3.1.*,!=3.2.*,!=3.3.*
Requires-Dist: backports.functools-lru-cache
Requires-Dist: six (>=1.11.0)
Requires-Dist: more-itertools (>=2.6)
Provides-Extra: docs
Requires-Dist: sphinx (>=1.8.2) ; extra == 'docs'
Requires-Dist: rst.linker (>=1.9) ; extra == 'docs'
Requires-Dist: jaraco.packaging (>=3.2) ; extra == 'docs'
Requires-Dist: docutils ; extra == 'docs'
Requires-Dist: alabaster ; extra == 'docs'
Requires-Dist: collective.checkdocs ; extra == 'docs'
Provides-Extra: testing
Requires-Dist: ddt ; extra == 'testing'
Requires-Dist: pytest (>=2.8) ; extra == 'testing'
Requires-Dist: pytest-mock ; extra == 'testing'
Requires-Dist: pytest-sugar (>=0.9.1) ; extra == 'testing'
Requires-Dist: pytest-testmon (>=0.9.7) ; extra == 'testing'
Requires-Dist: pytest-watch ; extra == 'testing'
Requires-Dist: pytest-xdist ; extra == 'testing'
Requires-Dist: coverage ; extra == 'testing'
Requires-Dist: codecov ; extra == 'testing'
Requires-Dist: pytest-cov ; extra == 'testing'
Requires-Dist: trustme (>=0.4.0) ; extra == 'testing'
Requires-Dist: pyopenssl ; extra == 'testing'
Requires-Dist: requests-unixsocket ; extra == 'testing'
